bigquery_agent/__init__.py
bigquery_agent/bigquery_helper.py
bigquery_helper/__init__.py
bigquery_helper/bigquery_helper.py
bigquery_agent-1.3.0.dist-info/METADATA
bigquery_agent-1.3.0.dist-info/WHEEL
bigquery_agent-1.3.0.dist-info/top_level.txt
bigquery_agent-1.3.0.dist-info/RECORD
