Metadata-Version: 2.1
Name: bigquery_agent
Version: 1.3.0
Summary: Library for creating agent around BigQuery
Author: Hlib Bochkarev
Author-email: glebuar@gmail.com
License: MIT
Requires-Dist: gemini_agents_toolkit<4,>=3.8
Requires-Dist: google-cloud-bigquery==3.27.0
